<?xml version="1.0" encoding="UTF-8"?>
<!DOCTYPE plist PUBLIC "-//Apple//DTD PLIST 1.0//EN" "http://www.apple.com/DTDs/PropertyList-1.0.dtd"/>

<plist version="1.0">
    <dict>
        <key>ROOT</key>
        <array>
            <dict>
                <key>id</key>
                <string>1382</string>
            </dict>
            <dict>
                <key>id</key>
                <string>1799</string>
                <key>Image</key>
                <dict>
                    <key>value</key>
                    <string>6467</string>
                </dict>
                <key>Click Sound</key>
                <dict>
                    <key>value</key>
                    <string>4113</string>
                </dict>
            </dict>
            <dict>
                <key>id</key>
                <string>2040</string>
                <key>Image</key>
                <dict>
                    <key>value</key>
                    <string>2038</string>
                </dict>
            </dict>
            <dict>
                <key>id</key>
                <string>2042</string>
                <key>Image</key>
                <dict>
                    <key>value</key>
                    <string>2038</string>
                </dict>
            </dict>
            <dict>
                <key>id</key>
                <string>2219</string>
                <key>Image</key>
                <dict>
                    <key>value</key>
                    <string>2234</string>
                </dict>
                <key>Click Sound</key>
                <dict>
                    <key>value</key>
                    <string>6519</string>
                </dict>
            </dict>
            <dict>
                <key>id</key>
                <string>2221</string>
                <key>Image</key>
                <dict>
                    <key>value</key>
                    <string>2240</string>
                </dict>
                <key>Click Sound</key>
                <dict>
                    <key>value</key>
                    <string>6519</string>
                </dict>
            </dict>
            <dict>
                <key>id</key>
                <string>2247</string>
                <key>Image</key>
                <dict>
                    <key>value</key>
                    <string>2248</string>
                </dict>
                <key>Click Sound</key>
                <dict>
                    <key>value</key>
                    <string>6519</string>
                </dict>
            </dict>
            <dict>
                <key>id</key>
                <string>2480</string>
                <key>Image</key>
                <dict>
                    <key>value</key>
                    <string>2234</string>
                </dict>
            </dict>
            <dict>
                <key>id</key>
                <string>2481</string>
                <key>Image</key>
                <dict>
                    <key>value</key>
                    <string>2240</string>
                </dict>
            </dict>
            <dict>
                <key>id</key>
                <string>2482</string>
                <key>Image</key>
                <dict>
                    <key>value</key>
                    <string>2248</string>
                </dict>
            </dict>
            <dict>
                <key>id</key>
                <string>2508</string>
                <key>Image</key>
                <dict>
                    <key>value</key>
                    <string>2234</string>
                </dict>
            </dict>
            <dict>
                <key>id</key>
                <string>2509</string>
                <key>Image</key>
                <dict>
                    <key>value</key>
                    <string>2240</string>
                </dict>
            </dict>
            <dict>
                <key>id</key>
                <string>2510</string>
                <key>Image</key>
                <dict>
                    <key>value</key>
                    <string>2248</string>
                </dict>
            </dict>
            <dict>
                <key>id</key>
                <string>2519</string>
            </dict>
            <dict>
                <key>id</key>
                <string>2521</string>
            </dict>
            <dict>
                <key>id</key>
                <string>2543</string>
                <key>Image</key>
                <dict>
                    <key>value</key>
                    <string>2038</string>
                </dict>
            </dict>
            <dict>
                <key>id</key>
                <string>2561</string>
            </dict>
            <dict>
                <key>id</key>
                <string>2673</string>
                <key>Image</key>
                <dict>
                    <key>value</key>
                    <string>2038</string>
                </dict>
                <key>Click Sound</key>
                <dict>
                    <key>value</key>
                    <string>6519</string>
                </dict>
            </dict>
            <dict>
                <key>id</key>
                <string>2697</string>
                <key>Image</key>
                <dict>
                    <key>value</key>
                    <string>2234</string>
                </dict>
            </dict>
            <dict>
                <key>id</key>
                <string>2698</string>
                <key>Image</key>
                <dict>
                    <key>value</key>
                    <string>2240</string>
                </dict>
            </dict>
            <dict>
                <key>id</key>
                <string>2699</string>
                <key>Image</key>
                <dict>
                    <key>value</key>
                    <string>2248</string>
                </dict>
            </dict>
            <dict>
                <key>id</key>
                <string>4008</string>
                <key>Image</key>
                <dict>
                    <key>value</key>
                    <string>4038</string>
                </dict>
                <key>Click Sound</key>
                <dict>
                    <key>value</key>
                    <string>6519</string>
                </dict>
            </dict>
            <dict>
                <key>id</key>
                <string>4006</string>
                <key>Image</key>
                <dict>
                    <key>value</key>
                    <string>2234</string>
                </dict>
                <key>Click Sound</key>
                <dict>
                    <key>value</key>
                    <string>4113</string>
                </dict>
            </dict>
            <dict>
                <key>id</key>
                <string>6477</string>
                <key>Image</key>
                <dict>
                    <key>value</key>
                    <string>6483</string>
                </dict>
                <key>Click Sound</key>
                <dict>
                    <key>value</key>
                    <string>6519</string>
                </dict>
            </dict>
            <dict>
                <key>id</key>
                <string>6555</string>
                <key>Image</key>
                <dict>
                    <key>value</key>
                    <string>4038</string>
                </dict>
                <key>Click Sound</key>
                <dict>
                    <key>value</key>
                    <string>6519</string>
                </dict>
            </dict>
            <dict>
                <key>id</key>
                <string>6769</string>
                <key>Image</key>
                <dict>
                    <key>value</key>
                    <string>6767</string>
                </dict>
            </dict>
            <dict>
                <key>id</key>
                <string>6771</string>
                <key>Image</key>
                <dict>
                    <key>value</key>
                    <string>6767</string>
                </dict>
                <key>Click Sound</key>
                <dict>
                    <key>value</key>
                    <string>6519</string>
                </dict>
            </dict>
            <dict>
                <key>id</key>
                <string>6774</string>
                <key>Image</key>
                <dict>
                    <key>value</key>
                    <string>6467</string>
                </dict>
                <key>Click Sound</key>
                <dict>
                    <key>value</key>
                    <string>4113</string>
                </dict>
            </dict>
            <dict>
                <key>id</key>
                <string>6776</string>
                <key>Image</key>
                <dict>
                    <key>value</key>
                    <string>6483</string>
                </dict>
                <key>Click Sound</key>
                <dict>
                    <key>value</key>
                    <string>6519</string>
                </dict>
            </dict>
        </array>
    </dict>
</plist>
